foo_bar_lib_probe/__init__.py
foo_bar_lib_probe/foo.py
foo_bar_lib_probe-0.3.0.dist-info/LICENSE
foo_bar_lib_probe-0.3.0.dist-info/METADATA
foo_bar_lib_probe-0.3.0.dist-info/WHEEL
foo_bar_lib_probe-0.3.0.dist-info/top_level.txt
foo_bar_lib_probe-0.3.0.dist-info/RECORD
